setup.py
tocker/__init__.py
tocker/fixtures.py
tocker.egg-info/PKG-INFO
tocker.egg-info/SOURCES.txt
tocker.egg-info/dependency_links.txt
tocker.egg-info/entry_points.txt
tocker.egg-info/requires.txt
tocker.egg-info/top_level.txt