Metadata-Version: 1.0
Name: tocker
Version: 0.1
Summary: TDD for Docker
Home-page: UNKNOWN
Author: Nam Ngo
Author-email: namngology@gmail.com
License: The MIT License (MIT)
Keywords: docker tdd testing test container
Platform: UNKNOWN
